event_ruler/build.py
event_ruler/__init__.py
event_ruler/_event_ruler.cpython-311-darwin.h
event_ruler/event_ruler_go.h
event_ruler/_event_ruler.cpython-311-darwin.so
event_ruler/event_ruler.c
event_ruler/go.py
event_ruler/event_ruler.py
event_ruler/event_ruler.go
event_ruler-0.3.0.dist-info/RECORD
event_ruler-0.3.0.dist-info/LICENSE
event_ruler-0.3.0.dist-info/WHEEL
event_ruler-0.3.0.dist-info/top_level.txt
event_ruler-0.3.0.dist-info/METADATA
