Metadata-Version: 2.1
Name: event-ruler
Version: 0.3.0
Summary: Test EventBridge pattern with Python locally
Home-page: https://github.com/tuananh/py-event-ruler
Author: Tuan Anh Tran
Author-email: me@tuananh.org
License: MIT License
Classifier: Programming Language :: Python :: 3
Classifier: License :: OSI Approved :: MIT License
Classifier: Operating System :: OS Independent
License-File: LICENSE
